prosigue/__init__.py
prosigue/command.py
prosigue/another_bookstores/__init__.py
prosigue/another_bookstores/do_hasta_time.py
prosigue/another_bookstores/movenatu.py
prosigue/read_bookstores/__init__.py
prosigue/read_bookstores/readme_do_hasta_time_help.py
prosigue/read_bookstores/readme_movenatu_help.py
prosigue/read_bookstores/readme_prosigue_help.py
prosigue/read_bookstores/show_de_principiofinal.py
prosigue/standard/__init__.py
prosigue/standard/principiofinal.py
prosigue-1.9.dist-info/METADATA
prosigue-1.9.dist-info/WHEEL
prosigue-1.9.dist-info/license.txt
prosigue-1.9.dist-info/top_level.txt
prosigue-1.9.dist-info/RECORD
